videotools/__init__.py
videotools/inventory.py
videotools/model.py
videotools/net.py
videotools/settings.py
videotools/utils.py
videotools/ci/__init__.py
videotools/parsers/__init__.py
videotools/parsers/cipher.py
videotools/parsers/git.py
videotools/parsers/inventory.py
videotools/parsers/net.py
videotools/resources/__init__.py
videotools/resources/appconfig.json
videotools/resources/applogging.json
videotools/resources/batch_executor_schema.json
videotools/resources/batch_schema.json
videotools/resources/inventory_schema.json
videotools/resources/remote_auth_schema.json
videotools/resources/remote_cmd_schema.json
videotools/resources/remote_executor_schema.json
videotools_aut_tools-1.3.0-5.7bbc440.macos.data/scripts/vitools.py
videotools_aut_tools-1.3.0.dist-info/METADATA
videotools_aut_tools-1.3.0.dist-info/WHEEL
videotools_aut_tools-1.3.0.dist-info/top_level.txt
videotools_aut_tools-1.3.0.dist-info/RECORD
